{"cameraMode":{"drawMode":0,"name":"Shaded","section":"Shading Mode"},"sceneLighting":true,"audioPlay":false,"sceneViewState":{"m_AlwaysRefresh":false,"showFog":true,"showSkybox":true,"showFlares":true,"showImageEffects":true,"showParticleSystems":true,"showVisualEffectGraphs":true,"m_FxEnabled":true},"in2DMode":false,"pivot":{"x":-0.46537283062934878,"y":2.194668769836426,"z":-2.1483535766601564},"rotation":{"x":0.39265483617782595,"y":-0.0038539862725883724,"z":0.0016867835074663163,"w":0.9197297096252441},"size":0.8660253882408142,"orthographic":false}